first_package_manager/__init__.py
first_package_manager/operations.py
first_package_manager-0.1.0.dist-info/WHEEL
first_package_manager-0.1.0.dist-info/entry_points.txt
first_package_manager-0.1.0.dist-info/METADATA
first_package_manager-0.1.0.dist-info/RECORD
