Metadata-Version: 2.3
Name: first-package-manager
Version: 0.1.0
Summary: the four basic operations as a package
Author: james
Author-email: james <james.paul@zohocorp.com>
Requires-Python: >=3.13
